polygon_cache/__init__.py
polygon_cache/cache.py
polygon_cache/tests/__init__.py
polygon_cache/tests/expected_values.py
polygon_cache/tests/test_cache.py
polygon_cache-0.1.2.dist-info/WHEEL
polygon_cache-0.1.2.dist-info/METADATA
polygon_cache-0.1.2.dist-info/RECORD
