Metadata-Version: 2.1
Name: polygon-cache
Version: 0.1.2
Summary: A package that caches polygon API calls and seamlessly calls the API multiple times to get all requested data.
License: MIT
Author: raymond-devries
Requires-Python: >=3.8,<4.0
Classifier: License :: OSI Approved :: MIT License
Classifier: Programming Language :: Python :: 3
Classifier: Programming Language :: Python :: 3.8
Requires-Dist: polygon-api-client (>=0.1.6,<0.2.0)
Requires-Dist: pytz (>=2020.1,<2021.0)
Requires-Dist: requests-cache (>=0.5.2,<0.6.0)
